fit_webview_bridge/__init__.py
fit_webview_bridge/wkwebview.cpython-313-darwin.so
fit_webview_bridge-0.2.8a4.dist-info/METADATA
fit_webview_bridge-0.2.8a4.dist-info/WHEEL
fit_webview_bridge-0.2.8a4.dist-info/RECORD
