Metadata-Version: 2.2
Name: fit-webview-bridge
Version: 0.2.8a4
Summary: Qt native WebView bridge with PySide6 bindings
Author: FIT Project
License: LGPL-3.0-or-later
Project-URL: Homepage, https://github.com/fit-project/fit-webview-bridge
Requires-Python: <3.14,>=3.11
Requires-Dist: PySide6==6.9.0
Requires-Dist: shiboken6==6.9.0
Requires-Dist: shiboken6-generator==6.9.0
